altimetry_downloader_aviso/__init__.py
altimetry_downloader_aviso/auth.py
altimetry_downloader_aviso/cli.py
altimetry_downloader_aviso/core.py
altimetry_downloader_aviso/tds_client.py
altimetry_downloader_aviso/catalog_client/client.py
altimetry_downloader_aviso/catalog_client/granule_discoverer.py
altimetry_downloader_aviso/catalog_client/geonetwork/__init__.py
altimetry_downloader_aviso/catalog_client/geonetwork/query_builder.py
altimetry_downloader_aviso/catalog_client/geonetwork/response_parser.py
altimetry_downloader_aviso/catalog_client/geonetwork/models/catalog_resp_model.py
altimetry_downloader_aviso/catalog_client/geonetwork/models/model.py
altimetry_downloader_aviso/catalog_client/geonetwork/models/product_resp_model.py
altimetry_downloader_aviso/catalog_client/resources/tds_layout.yaml
altimetry_downloader_aviso-0.2.2.dist-info/licenses/LICENCE
altimetry_downloader_aviso-0.2.2.dist-info/METADATA
altimetry_downloader_aviso-0.2.2.dist-info/WHEEL
altimetry_downloader_aviso-0.2.2.dist-info/entry_points.txt
altimetry_downloader_aviso-0.2.2.dist-info/top_level.txt
altimetry_downloader_aviso-0.2.2.dist-info/RECORD
